vnpy/__init__.py
vnpy/api/__init__.py
vnpy/api/ctp/__init__.py
vnpy/api/ctp/ctp_data_type.py
vnpy/api/ctp/thostmduserapi.dll
vnpy/api/ctp/thosttraderapi.dll
vnpy/api/ctp/vnctpmd.pyd
vnpy/api/ctp/vnctptd.pyd
vnpy/event/__init__.py
vnpy/event/eventEngine.py
vnpy/event/eventType.py
vnpy/trader/VT_setting.json
vnpy/trader/__init__.py
vnpy/trader/uiBasicWidget.py
vnpy/trader/uiMainWindow.py
vnpy/trader/uiQt.py
vnpy/trader/vtConstant.py
vnpy/trader/vtEngine.py
vnpy/trader/vtEvent.py
vnpy/trader/vtFunction.py
vnpy/trader/vtGateway.py
vnpy/trader/vtGlobal.py
vnpy/trader/vtObject.py
vnpy/trader/vtText.py
vnpy/trader/app/__init__.py
vnpy/trader/app/algoTrading/__init__.py
vnpy/trader/app/algoTrading/algoEngine.py
vnpy/trader/app/algoTrading/algoTemplate.py
vnpy/trader/app/algoTrading/testRpc.py
vnpy/trader/app/algoTrading/uiAlgoManager.py
vnpy/trader/app/algoTrading/uiAlgoWidget.py
vnpy/trader/app/algoTrading/algo/__init__.py
vnpy/trader/app/algoTrading/algo/arbitrageAlgo.py
vnpy/trader/app/algoTrading/algo/blAlgo.py
vnpy/trader/app/algoTrading/algo/dmaAlgo.py
vnpy/trader/app/algoTrading/algo/icebergAlgo.py
vnpy/trader/app/algoTrading/algo/sniperAlgo.py
vnpy/trader/app/algoTrading/algo/stAlgo.py
vnpy/trader/app/algoTrading/algo/stopAlgo.py
vnpy/trader/app/algoTrading/algo/twapAlgo.py
vnpy/trader/app/ctaStrategy/__init__.py
vnpy/trader/app/ctaStrategy/ctaBacktesting.py
vnpy/trader/app/ctaStrategy/ctaBase.py
vnpy/trader/app/ctaStrategy/ctaEngine.py
vnpy/trader/app/ctaStrategy/ctaHistoryData.py
vnpy/trader/app/ctaStrategy/ctaTemplate.py
vnpy/trader/app/ctaStrategy/uiCtaWidget.py
vnpy/trader/app/ctaStrategy/language/__init__.py
vnpy/trader/app/ctaStrategy/language/chinese/__init__.py
vnpy/trader/app/ctaStrategy/language/chinese/text.py
vnpy/trader/app/ctaStrategy/language/english/__init__.py
vnpy/trader/app/ctaStrategy/language/english/text.py
vnpy/trader/app/ctaStrategy/strategy/__init__.py
vnpy/trader/app/ctaStrategy/strategy/strategyAtrRsi.py
vnpy_light-0.0.1.dist-info/LICENSE
vnpy_light-0.0.1.dist-info/METADATA
vnpy_light-0.0.1.dist-info/WHEEL
vnpy_light-0.0.1.dist-info/top_level.txt
vnpy_light-0.0.1.dist-info/RECORD
