Metadata-Version: 2.1
Name: vnpy-light
Version: 0.0.1
Summary: A easier way to install vnpy
Home-page: https://github.com/hzhu212/vnpy-light
Author: hzhu212
Author-email: zhuhe212@163.com
License: MIT
Keywords: vnpy quant quantitative investment trading algotrading
Platform: UNKNOWN
Classifier: Development Status :: 3 - Alpha
Classifier: Intended Audience :: Developers
Classifier: Natural Language :: English
Classifier: License :: OSI Approved :: MIT License
Classifier: Operating System :: Microsoft :: Windows
Classifier: Programming Language :: Python :: 3
Classifier: Programming Language :: Python :: 3.5
Classifier: Programming Language :: Python :: 3.6
Classifier: Programming Language :: Python :: 3.7
Classifier: Programming Language :: Python :: Implementation :: CPython
Classifier: Topic :: Office/Business :: Financial :: Investment
Requires-Python: >=3.5
Requires-Dist: pymongo
